galaxy/__init__.py
galaxy/py.typed
galaxy/datatypes/__init__.py
galaxy/datatypes/_schema.py
galaxy/datatypes/annotation.py
galaxy/datatypes/anvio.py
galaxy/datatypes/assembly.py
galaxy/datatypes/binary.py
galaxy/datatypes/blast.py
galaxy/datatypes/chain.py
galaxy/datatypes/checkers.py
galaxy/datatypes/chrominfo.py
galaxy/datatypes/constructive_solid_geometry.py
galaxy/datatypes/coverage.py
galaxy/datatypes/data.py
galaxy/datatypes/flow.py
galaxy/datatypes/genetics.py
galaxy/datatypes/gis.py
galaxy/datatypes/goldenpath.py
galaxy/datatypes/graph.py
galaxy/datatypes/hdf5.py
galaxy/datatypes/images.py
galaxy/datatypes/interval.py
galaxy/datatypes/isa.py
galaxy/datatypes/larch.py
galaxy/datatypes/media.py
galaxy/datatypes/metacyto.py
galaxy/datatypes/metadata.py
galaxy/datatypes/microarrays.py
galaxy/datatypes/molecules.py
galaxy/datatypes/mothur.py
galaxy/datatypes/msa.py
galaxy/datatypes/neo4j.py
galaxy/datatypes/ngsindex.py
galaxy/datatypes/phylip.py
galaxy/datatypes/plant_tribes.py
galaxy/datatypes/proteomics.py
galaxy/datatypes/protocols.py
galaxy/datatypes/qiime2.py
galaxy/datatypes/qualityscore.py
galaxy/datatypes/registry.py
galaxy/datatypes/sequence.py
galaxy/datatypes/set_metadata_tool.xml
galaxy/datatypes/sniff.py
galaxy/datatypes/spaln.py
galaxy/datatypes/speech.py
galaxy/datatypes/tabular.py
galaxy/datatypes/text.py
galaxy/datatypes/tracks.py
galaxy/datatypes/triples.py
galaxy/datatypes/upload_util.py
galaxy/datatypes/xml.py
galaxy/datatypes/converters/__init__.py
galaxy/datatypes/converters/archive_to_directory.xml
galaxy/datatypes/converters/bam_to_bai.xml
galaxy/datatypes/converters/bam_to_bigwig_converter.xml
galaxy/datatypes/converters/bcf_bcf_uncompressed_converter.xml
galaxy/datatypes/converters/bed_gff_or_vcf_to_bigwig_converter.xml
galaxy/datatypes/converters/bed_to_fli_converter.xml
galaxy/datatypes/converters/bed_to_gff_converter.py
galaxy/datatypes/converters/bed_to_gff_converter.xml
galaxy_data-25.0.3.dist-info/licenses/LICENSE
galaxy_data-25.0.3.dist-info/METADATA
galaxy_data-25.0.3.dist-info/WHEEL
galaxy_data-25.0.3.dist-info/entry_points.txt
galaxy_data-25.0.3.dist-info/top_level.txt
galaxy_data-25.0.3.dist-info/RECORD
