Metadata-Version: 2.4
Name: galaxy-data
Version: 25.0.3
Summary: Galaxy datatype framework and datatypes
Home-page: https://github.com/galaxyproject/galaxy
Author: Galaxy Project and Community
Author-email: galaxy-committers@lists.galaxyproject.org
License: AFL
Keywords: Galaxy
Classifier: Development Status :: 5 - Production/Stable
Classifier: Environment :: Console
Classifier: Intended Audience :: Developers
Classifier: License :: OSI Approved :: Academic Free License (AFL)
Classifier: Natural Language :: English
Classifier: Operating System :: POSIX
Classifier: Programming Language :: Python :: 3
Classifier: Programming Language :: Python :: 3.9
Classifier: Programming Language :: Python :: 3.10
Classifier: Programming Language :: Python :: 3.11
Classifier: Programming Language :: Python :: 3.12
Classifier: Programming Language :: Python :: 3.13
Classifier: Topic :: Software Development
Classifier: Topic :: Software Development :: Code Generators
Classifier: Topic :: Software Development :: Testing
Requires-Python: >=3.9
License-File: LICENSE
Requires-Dist: galaxy-files
Requires-Dist: galaxy-objectstore
Requires-Dist: galaxy-schema
Requires-Dist: galaxy-tool-util
Requires-Dist: galaxy-util[image-util,template]
Requires-Dist: alembic
Requires-Dist: bdbag>=1.6.3
Requires-Dist: bx-python
Requires-Dist: dnspython
Requires-Dist: galaxy-sequence-utils
Requires-Dist: h5grove>=1.2.1
Requires-Dist: h5py
Requires-Dist: isa-rwval>=0.10.11
Requires-Dist: isal>=1.7.0
Requires-Dist: MarkupSafe
Requires-Dist: msal
Requires-Dist: mrcfile
Requires-Dist: numpy
Requires-Dist: parsley
Requires-Dist: pycryptodome
Requires-Dist: pydantic[email]>=2.7.4
Requires-Dist: pylibmagic
Requires-Dist: pypng
Requires-Dist: python-magic
Requires-Dist: pysam>=0.21
Requires-Dist: rocrate
Requires-Dist: social-auth-core>=4.5.0
Requires-Dist: SQLAlchemy!=2.0.36,<2.1,>=2.0
Requires-Dist: tifffile
Requires-Dist: typing-extensions
Dynamic: license-file
